{
  "project_info": {
    "project_number": "902425976202",
    "project_id": "pixefly-81fb9",
    "storage_bucket": "pixefly-81fb9.firebasestorage.app"
  },
  "client": [
    {
      "client_info": {
        "mobilesdk_app_id": "1:902425976202:android:d6c3c4db84d8acbf8dfc73",
        "android_client_info": {
          "package_name": "com.pixelfy.pixelfy"
        }
      },
      "oauth_client": [],
      "api_key": [
        {
          "current_key": "AIzaSyCslkMc3Lbj8oUVBrUUXo-JnJwNBmXyi5g"
        }
      ],
      "services": {
        "appinvite_service": {
          "other_platform_oauth_client": []
        }
      }
    }
  ],
  "configuration_version": "1"
}